odoo/addons/sale_product_packaging_container_deposit/README.rst
odoo/addons/sale_product_packaging_container_deposit/__init__.py
odoo/addons/sale_product_packaging_container_deposit/__manifest__.py
odoo/addons/sale_product_packaging_container_deposit/i18n/es.po
odoo/addons/sale_product_packaging_container_deposit/i18n/fr.po
odoo/addons/sale_product_packaging_container_deposit/i18n/it.po
odoo/addons/sale_product_packaging_container_deposit/i18n/sale_product_packaging_container_deposit.pot
odoo/addons/sale_product_packaging_container_deposit/models/__init__.py
odoo/addons/sale_product_packaging_container_deposit/models/sale_order.py
odoo/addons/sale_product_packaging_container_deposit/models/sale_order_line.py
odoo/addons/sale_product_packaging_container_deposit/models/stock_move.py
odoo/addons/sale_product_packaging_container_deposit/readme/CONTRIBUTORS.rst
odoo/addons/sale_product_packaging_container_deposit/readme/DESCRIPTION.rst
odoo/addons/sale_product_packaging_container_deposit/static/description/icon.png
odoo/addons/sale_product_packaging_container_deposit/static/description/index.html
odoo/addons/sale_product_packaging_container_deposit/tests/__init__.py
odoo/addons/sale_product_packaging_container_deposit/tests/test_sale_product_packaging_container_deposit.py
odoo_addon_sale_product_packaging_container_deposit-16.0.1.1.1.2.dist-info/METADATA
odoo_addon_sale_product_packaging_container_deposit-16.0.1.1.1.2.dist-info/WHEEL
odoo_addon_sale_product_packaging_container_deposit-16.0.1.1.1.2.dist-info/top_level.txt
odoo_addon_sale_product_packaging_container_deposit-16.0.1.1.1.2.dist-info/RECORD
