Metadata-Version: 2.1
Name: odoo-addon-sale_product_packaging_container_deposit
Version: 16.0.1.1.1.2
Summary: Sale Product Packaging Container Deposit
Home-page: https://github.com/OCA/sale-workflow
Author: Camptocamp, BCIM, Odoo Community Association (OCA)
Author-email: support@odoo-community.org
License: AGPL-3
Classifier: Programming Language :: Python
Classifier: Framework :: Odoo
Classifier: Framework :: Odoo :: 16.0
Classifier: License :: OSI Approved :: GNU Affero General Public License v3
Classifier: Development Status :: 4 - Beta
Requires-Python: >=3.10
Requires-Dist: odoo-addon-product-packaging-container-deposit<16.1dev,>=16.0dev
Requires-Dist: odoo<16.1dev,>=16.0a
